[
  {
    "category": "張老師",
    "items": [
      { "text": "聯絡電話：02-2737-6310" },
      { "text": "校內分機：6310" },
      { "text": "Email：waiting103@mail.ntust.edu.tw", "link": "mailto:waiting103@mail.ntust.edu.tw" }
    ]
  },
  {
    "category": "侯老師",
    "items": [
      { "text": "聯絡電話：02-2730-3270" },
      { "text": "校內分機：3270" },
      { "text": "Email：hou1223@mail.ntust.edu.tw", "link": "mailto:hou1223@mail.ntust.edu.tw" }
    ]
  },
  {
    "category": "謝老師",
    "items": [
      { "text": "聯絡電話：02-2730-1250" },
      { "text": "校內分機：1250" },
      { "text": "Email：bluefish@mail.ntust.edu.tw", "link": "mailto:bluefish@mail.ntust.edu.tw" }
    ]
  },
  {
    "category": "蔡老師",
    "items": [
      { "text": "聯絡電話：02-2730-3622" },
      { "text": "校內分機：3622" },
      { "text": "Email：tinghao211065@mail.ntust.edu.tw", "link": "mailto:tinghao211065@mail.ntust.edu.tw" }
    ]
  }
]
